{
  "parent": "minecraft:recipes/root",
  "rewards": {
    "recipes": [
      "minecraft:cut_iron_slab_from_cut_iron_stonecutting"
    ]
  },
  "criteria": {
    "has_cut_iron": {
      "trigger": "minecraft:inventory_changed",
      "conditions": {
        "items": [
          {
            "items": [
              "wich:cut_iron"
            ]
          }
        ]
      }
    },
    "has_the_recipe": {
      "trigger": "minecraft:recipe_unlocked",
      "conditions": {
        "recipe": "minecraft:cut_iron_slab_from_cut_iron_stonecutting"
      }
    }
  },
  "requirements": [
    [
      "has_cut_iron",
      "has_the_recipe"
    ]
  ]
}