{
  "parent": "minecraft:recipes/root",
  "rewards": {
    "recipes": [
      "wich:beige_concrete_wall_from_beige_concrete_stonecutting"
    ]
  },
  "criteria": {
    "has_beige_concrete": {
      "trigger": "minecraft:inventory_changed",
      "conditions": {
        "items": [
          {
            "items": [
              "wich:beige_concrete"
            ]
          }
        ]
      }
    },
    "has_the_recipe": {
      "trigger": "minecraft:recipe_unlocked",
      "conditions": {
        "recipe": "wich:beige_concrete_wall_from_beige_concrete_stonecutting"
      }
    }
  },
  "requirements": [
    [
      "has_beige_concrete",
      "has_the_recipe"
    ]
  ]
}