{
  "parent": "minecraft:recipes/root",
  "rewards": {
    "recipes": [
      "wich:end_shale_brick_slab_from_end_shale_stonecutting"
    ]
  },
  "criteria": {
    "has_end_shale": {
      "trigger": "minecraft:inventory_changed",
      "conditions": {
        "items": [
          {
            "items": [
              "wich:end_shale"
            ]
          }
        ]
      }
    },
    "has_the_recipe": {
      "trigger": "minecraft:recipe_unlocked",
      "conditions": {
        "recipe": "wich:end_shale_brick_slab_from_end_shale_stonecutting"
      }
    }
  },
  "requirements": [
    [
      "has_end_shale",
      "has_the_recipe"
    ]
  ]
}