{
  "parent": "minecraft:recipes/root",
  "rewards": {
    "recipes": [
      "wich:jungle_wood_slab_from_jungle_wood_woodcutting"
    ]
  },
  "criteria": {
    "has_jungle_wood": {
      "trigger": "minecraft:inventory_changed",
      "conditions": {
        "items": [
          {
            "items": [
              "minecraft:jungle_wood"
            ]
          }
        ]
      }
    },
    "has_the_recipe": {
      "trigger": "minecraft:recipe_unlocked",
      "conditions": {
        "recipe": "wich:jungle_wood_slab_from_jungle_wood_woodcutting"
      }
    }
  },
  "requirements": [
    [
      "has_jungle_wood",
      "has_the_recipe"
    ]
  ]
}